cecil/__init__.py
cecil/client.py
cecil/errors.py
cecil/models.py
cecil/version.py
cecil/xarray.py
cecil-0.1.7.dist-info/METADATA
cecil-0.1.7.dist-info/WHEEL
cecil-0.1.7.dist-info/licenses/LICENSE.txt
cecil-0.1.7.dist-info/RECORD
