Metadata-Version: 2.4
Name: cecil
Version: 0.1.7
Summary: Python SDK for Cecil Earth
License-Expression: MIT
License-File: LICENSE.txt
Classifier: Development Status :: 4 - Beta
Classifier: License :: OSI Approved :: MIT License
Classifier: Operating System :: OS Independent
Classifier: Programming Language :: Python :: 3
Requires-Python: >=3.10
Requires-Dist: boto3<2.0.0,>=1.42.0
Requires-Dist: dask>=2025.9.1
Requires-Dist: pyarrow<23.0.0,>=22.0.0
Requires-Dist: pydantic<3.0.0,>=2.11.9
Requires-Dist: requests<3.0.0,>=2.32.5
Requires-Dist: rioxarray<1.0.0,>=0.19.0
Requires-Dist: xarray>=2025.6.1
